bluish/__init__.py
bluish/__main__.py
bluish/app.py
bluish/core.py
bluish/expressions.py
bluish/logging.py
bluish/process.py
bluish/py.typed
bluish/safe_string.py
bluish/schemas.py
bluish/utils.py
bluish/actions/__init__.py
bluish/actions/base.py
bluish/actions/core.py
bluish/actions/docker.py
bluish/actions/git.py
bluish/actions/linux.py
bluish/actions/macos.py
bluish/nodes/__init__.py
bluish/nodes/environment.py
bluish/nodes/job.py
bluish/nodes/step.py
bluish/nodes/workflow.py
bluish-0.9.16.dist-info/LICENSE
bluish-0.9.16.dist-info/METADATA
bluish-0.9.16.dist-info/WHEEL
bluish-0.9.16.dist-info/entry_points.txt
bluish-0.9.16.dist-info/top_level.txt
bluish-0.9.16.dist-info/RECORD
