Metadata-Version: 2.2
Name: bluish
Version: 0.9.16
Summary: A CI/CD tool
Home-page: https://github.com/luismedel/bluish
Author: Luis Medel <luis@luismedel.com>
Author-email: Luis Medel <luis@luismedel.com>
Project-URL: Github, https://github.com/luismedel/bluish
Project-URL: Homepage, https://github.com/luismedel/bluish
Classifier: Intended Audience :: Developers
Classifier: Programming Language :: Python :: 3
Classifier: License :: OSI Approved :: MIT License
Classifier: Operating System :: OS Independent
Classifier: Typing :: Typed
Requires-Python: >=3.10
License-File: LICENSE
Requires-Dist: python-dotenv==1.0.1
Requires-Dist: pyyaml==6.0.2
Requires-Dist: click==8.1.7
Requires-Dist: flask==3.0.3
Requires-Dist: lark==1.2.2
Requires-Dist: typing-extensions==4.12.2
